{
    "version": 1,
    "license": "CC-BY-SA-3.0",
    "copyright": "Taken from https://github.com/Simple-Station/Parkstation/commit/4b65cdf873a29cdcc796581a61095ebe54f1c959",
    "size": {
        "x": 32,
        "y": 32
    },
    "states": [
        {
            "name": "id_overlay"
        },
        {
            "name": "equipped-BELT",
            "directions": 4
        },
        {
            "name": "insert_overlay"
        },
        {
            "name": "light_overlay"
        },
        {
            "name": "pda-css"
        },
        {
            "name": "pda"
        }
    ]
}
